MANIFEST.in
README.md
setup.py
django_pipedrive.egg-info/PKG-INFO
django_pipedrive.egg-info/SOURCES.txt
django_pipedrive.egg-info/dependency_links.txt
django_pipedrive.egg-info/top_level.txt
pipedrive/__init__.py
pipedrive/fields.py
pipedrive/models.py
pipedrive/pipedrive_client.py
pipedrive/tests.py
pipedrive/urls.py
pipedrive/utils.py
pipedrive/views.py
pipedrive/migrations/0001_initial.py
pipedrive/migrations/0002_auto_20170423_2217.py
pipedrive/migrations/0003_fieldmodification.py
pipedrive/migrations/0004_auto_20170502_1701.py
pipedrive/migrations/0005_auto_20170510_1253.py
pipedrive/migrations/0006_auto_20170512_1945.py
pipedrive/migrations/0007_auto_20170519_0052.py
pipedrive/migrations/0008_auto_20170530_1548.py
pipedrive/migrations/0009_enumfield.py
pipedrive/migrations/__init__.py
test_app/__init__.py
test_app/admin.py
test_app/models.py
test_app/tests.py
test_app/views.py
test_app/migrations/0001_initial.py
test_app/migrations/__init__.py