Metadata-Version: 1.1
Name: django-pipedrive
Version: 0.1.14
Summary: A Django app to syncronice data with Pipedrive.
Home-page: https://github.com/MasAval/django_pipedrive
Author: UNKNOWN
Author-email: gussoto@ug.uchile.cl
License: BSD License
Platform: UNKNOWN
Classifier: Environment :: Web Environment
Classifier: Framework :: Django
Classifier: Framework :: Django :: 1.8
Classifier: Intended Audience :: Developers
Classifier: License :: OSI Approved :: BSD License
Classifier: Operating System :: OS Independent
Classifier: Programming Language :: Python
Classifier: Programming Language :: Python :: 2.7
Classifier: Topic :: Internet :: WWW/HTTP
Classifier: Topic :: Internet :: WWW/HTTP :: Dynamic Content
